{
   "constantName": "pbadm.homepage",
   "extendsPage": null,
   "modelView": {
      "components": [
         {
            "resource": "virtualDomains.pbadmNonAdmPages",
            "name": "pbPages",
            "type": "resource",
            "staticData": []
         },
         {
            "components": [
               {
                  "components": [
                     {
                        "documentation": "test",
                        "imageUrl": "",
                        "labelStyle": "",
                        "name": "virtualDomainLink",
                        "description": "Virtual Domain Composer",
                        "style": "list-link",
                        "label": "",
                        "type": "link",
                        "replaceView": true,
                        "url": "/banner-sspb-test-app/virtualDomainComposer/loadVirtualDomain"
                     },
                     {
                        "name": "visualPageComposerLink",
                        "description": "Visual Page Composer",
                        "style": "list-link",
                        "type": "link",
                        "replaceView": true,
                        "url": "/banner-sspb-test-app/visualPageModelComposer/loadComposerPage"
                     },
                     {
                        "name": "cssStyleSheetManagerLink",
                        "description": "CSS Stylesheet Manager",
                        "style": "list-link",
                        "type": "link",
                        "replaceView": true,
                        "url": "/banner-sspb-test-app/cssManager/loadCssManagerPage"
                     },
                     {
                        "name": "pageRolesLink",
                        "description": "Page Roles",
                        "style": "list-link",
                        "type": "link",
                        "replaceView": true,
                        "url": "/banner-sspb-test-app/customPage/page/pbadm.PageRoles"
                     },
                     {
                        "name": "virtualDomainRolesLink",
                        "description": "Virtual Domain Roles",
                        "style": "list-link",
                        "type": "link",
                        "replaceView": true,
                        "url": "/banner-sspb-test-app/customPage/page/pbadm.VirtualDomainRoles"
                     },
                     {
                        "name": "exportPageLink",
                        "description": "Export Pages",
                        "style": "list-link",
                        "type": "link",
                        "replaceView": true,
                        "url": "/banner-sspb-test-app/customPage/page/pbadm.ExportPages"
                     },
                     {
                        "name": "exportDomainsLink",
                        "description": "Export Domains",
                        "style": "list-link",
                        "type": "link",
                        "replaceView": true,
                        "url": "/banner-sspb-test-app/customPage/page/pbadm.ExportVirtualDomains"
                     },
                     {
                        "name": "exportCssStylesheetsLink",
                        "description": "Export Css Stylesheets",
                        "style": "list-link",
                        "type": "link",
                        "replaceView": true,
                        "url": "/banner-sspb-test-app/customPage/page/pbadm.ExportCss"
                     }
                  ],
                  "nextButtonLabel": "Next",
                  "name": "adminPagesForm",
                  "showInitially": false,
                  "label": "Page Builder Administration",
                  "type": "form"
               },
               {
                  "components": [{
                     "onClick": "window.location.assign(rootWebApp + 'customPage/page/' + currentSelection.CONSTANT_NAME);",
                     "name": "pageList",
                     "onLoad": "$adminPagesForm.$visible = false;\nif (typeof($$user) !== 'undefined') {\n    if ($$user.authenticated) {\n        if ($$user.authorities && $$user.authorities.length > 0 &&\n            _.findWhere($$user.authorities, {assignedSelfServiceRole: \"WTAILORADMIN\"})) {\n            $adminPagesForm.$visible = true;\n        }\n   }\n}",
                     "pageSize": 0,
                     "model": "pbPages",
                     "allowReload": false,
                     "loadInitially": true,
                     "type": "list",
                     "parameters": {},
                     "value": "CONSTANT_NAME",
                     "required": false
                  }],
                  "nextButtonLabel": "Next",
                  "name": "pageForm",
                  "showInitially": true,
                  "label": "Runtime Pages",
                  "type": "form"
               }
            ],
            "name": "pageBlock",
            "showInitially": true,
            "type": "block"
         }
      ],
      "name": "homepage",
      "scriptingLanguage": "JavaScript",
      "title": "Page Builder Home",
      "type": "page",
      "importCSS": "pbadm.homePageCss"
   },
   "fileTimestamp": "2016-01-08T13:22:33Z",
   "pageRoles": [
      {
         "allow": true,
         "roleName": "GUEST"
      },
      {
         "allow": true,
         "roleName": "WEBUSER"
      }
   ]
}